freckles_adapter_nsbl/__init__.py
freckles_adapter_nsbl/defaults.py
freckles_adapter_nsbl/freckles_adapter_nsbl.py
freckles_adapter_nsbl/freckles_cli_plugin_nsbl.py
freckles_adapter_nsbl/frkl.info
freckles_adapter_nsbl/nsbl_freckles_callback.py
freckles_adapter_nsbl/external/nsbl-community/frecklets/.gitkeep
freckles_adapter_nsbl/external/nsbl-community/resources/.gitkeep
freckles_adapter_nsbl/external/nsbl-default/frecklets/.gitkeep
freckles_adapter_nsbl/external/nsbl-default/resources/.gitkeep
freckles_adapter_nsbl/external/nsbl-plugins/.gitignore
freckles_adapter_nsbl/external/nsbl-plugins/LICENSE
freckles_adapter_nsbl/external/nsbl-plugins/README.md
freckles_adapter_nsbl/external/nsbl-plugins/action_plugins/freckles_facts.py
freckles_adapter_nsbl/external/nsbl-plugins/action_plugins/frecklet_result.py
freckles_adapter_nsbl/external/nsbl-plugins/action_plugins/install.py
freckles_adapter_nsbl/external/nsbl-plugins/action_plugins/set_platform_fact.py
freckles_adapter_nsbl/external/nsbl-plugins/callback_plugins/default_to_file.py
freckles_adapter_nsbl/external/nsbl-plugins/callback_plugins/default_to_file.py.license
freckles_adapter_nsbl/external/nsbl-plugins/callback_plugins/freckles_callback.py
freckles_adapter_nsbl/external/nsbl-plugins/callback_plugins/freckles_callback.py.license
freckles_adapter_nsbl/external/nsbl-plugins/filter_plugins/freckles_filters.py
freckles_adapter_nsbl/external/nsbl-plugins/library/asdf.py
freckles_adapter_nsbl/external/nsbl-plugins/library/conda.py
freckles_adapter_nsbl/external/nsbl-plugins/library/freckles_facts.license
freckles_adapter_nsbl/external/nsbl-plugins/library/freckles_facts.py
freckles_adapter_nsbl/external/nsbl-plugins/library/frecklet_result.py
freckles_adapter_nsbl/external/nsbl-plugins/library/install.py
freckles_adapter_nsbl/external/nsbl-plugins/library/mac_pkg.py
freckles_adapter_nsbl/external/nsbl-plugins/library/mac_pkg.py.license
freckles_adapter_nsbl/external/nsbl-plugins/library/nix.py
freckles_adapter_nsbl-1.0.0.dist-info/AUTHORS.rst
freckles_adapter_nsbl-1.0.0.dist-info/LICENSE
freckles_adapter_nsbl-1.0.0.dist-info/METADATA
freckles_adapter_nsbl-1.0.0.dist-info/WHEEL
freckles_adapter_nsbl-1.0.0.dist-info/entry_points.txt
freckles_adapter_nsbl-1.0.0.dist-info/top_level.txt
freckles_adapter_nsbl-1.0.0.dist-info/RECORD
