Metadata-Version: 2.1
Name: freckles-adapter-nsbl
Version: 1.0.0
Summary: A freckles adapter to run Ansible playbooks.
Home-page: https://gitlab.com/frkl/freckles_adapter_nsbl
Author: Markus Binsteiner
Author-email: markus@frkl.io
License: "The Parity Public License 6.0.0"
Platform: any
Classifier: Development Status :: 4 - Beta
Classifier: Programming Language :: Python
Requires-Python: !=3.0.*,!=3.1.*,!=3.2.*,!=3.3.*,!=3.4.*,>=2.7
Requires-Dist: freckles (>=1.0.0)
Requires-Dist: nsbl (>=1.0.0)
Provides-Extra: ansible
Requires-Dist: ansible ; extra == 'ansible'
Requires-Dist: jmespath ; extra == 'ansible'
Requires-Dist: pywinrm ; extra == 'ansible'
Provides-Extra: develop
Requires-Dist: flake8 ; extra == 'develop'
Requires-Dist: ipython ; extra == 'develop'
Requires-Dist: black ; extra == 'develop'
Requires-Dist: pip-tools ; extra == 'develop'
Requires-Dist: pre-commit ; extra == 'develop'
Requires-Dist: watchdog ; extra == 'develop'
Requires-Dist: wheel ; extra == 'develop'
Requires-Dist: pipdeptree ; extra == 'develop'
Requires-Dist: isort ; extra == 'develop'
Requires-Dist: setuptools-scm ; extra == 'develop'
Provides-Extra: docs
Requires-Dist: Sphinx ; extra == 'docs'
Requires-Dist: recommonmark ; extra == 'docs'
Provides-Extra: testing
Requires-Dist: pytest ; extra == 'testing'
Requires-Dist: more-itertools (==5.0.0) ; extra == 'testing'
Requires-Dist: pytest-cov ; extra == 'testing'
Requires-Dist: tox ; extra == 'testing'
